README.md
setup.py
teamtrees/__init__.py
teamtrees/cli.py
teamtrees/counter.py
teamtrees/donations.py
teamtrees.egg-info/PKG-INFO
teamtrees.egg-info/SOURCES.txt
teamtrees.egg-info/dependency_links.txt
teamtrees.egg-info/entry_points.txt
teamtrees.egg-info/requires.txt
teamtrees.egg-info/top_level.txt