Metadata-Version: 2.1
Name: teamtrees
Version: 1.0.0
Summary: Get data from official TeamTrees website
Home-page: https://github.com/nm17/teamtrees
Author: NeverMine17
Author-email: dannevergame@gmail.com
License: MIT
Platform: UNKNOWN
Classifier: Development Status :: 5 - Production/Stable
Classifier: Environment :: Console
Classifier: Intended Audience :: End Users/Desktop
Classifier: License :: OSI Approved :: MIT License
Classifier: Operating System :: OS Independent
Requires-Python: >=3.5
